iris_pgwire/__init__.py
iris_pgwire/backend_selector.py
iris_pgwire/bulk_executor.py
iris_pgwire/column_validator.py
iris_pgwire/config_schema.py
iris_pgwire/constitutional.py
iris_pgwire/copy_handler.py
iris_pgwire/csv_processor.py
iris_pgwire/dbapi_connection_pool.py
iris_pgwire/dbapi_executor.py
iris_pgwire/debug_tracer.py
iris_pgwire/health_checker.py
iris_pgwire/integratedml.py
iris_pgwire/iris_constructs.py
iris_pgwire/iris_executor.py
iris_pgwire/iris_log_handler.py
iris_pgwire/iris_user_management.py
iris_pgwire/observability.py
iris_pgwire/performance_monitor.py
iris_pgwire/protocol.py
iris_pgwire/schema_mapper.py
iris_pgwire/server.py
iris_pgwire/type_mapping.py
iris_pgwire/vector_metrics.py
iris_pgwire/vector_optimizer.py
iris_pgwire/auth/__init__.py
iris_pgwire/auth/auth_selector.py
iris_pgwire/auth/gssapi_auth.py
iris_pgwire/auth/oauth_bridge.py
iris_pgwire/auth/scram.py
iris_pgwire/auth/wallet_credentials.py
iris_pgwire/catalog/__init__.py
iris_pgwire/catalog/catalog_functions.py
iris_pgwire/catalog/catalog_router.py
iris_pgwire/catalog/oid_generator.py
iris_pgwire/catalog/pg_attrdef.py
iris_pgwire/catalog/pg_attribute.py
iris_pgwire/catalog/pg_class.py
iris_pgwire/catalog/pg_constraint.py
iris_pgwire/catalog/pg_index.py
iris_pgwire/catalog/pg_namespace.py
iris_pgwire/catalog/pg_type.py
iris_pgwire/conversions/__init__.py
iris_pgwire/conversions/bulk_insert.py
iris_pgwire/conversions/date_horolog.py
iris_pgwire/conversions/ddl_idempotency.py
iris_pgwire/conversions/ddl_splitter.py
iris_pgwire/conversions/json_path.py
iris_pgwire/conversions/vector_syntax.py
iris_pgwire/models/__init__.py
iris_pgwire/models/backend_config.py
iris_pgwire/models/connection_pool_state.py
iris_pgwire/models/dbapi_connection.py
iris_pgwire/models/ipm_metadata.py
iris_pgwire/models/vector_query_request.py
iris_pgwire/quality/__init__.py
iris_pgwire/quality/__main__.py
iris_pgwire/quality/code_quality_validator.py
iris_pgwire/quality/documentation_validator.py
iris_pgwire-1.2.34.dist-info/METADATA
iris_pgwire-1.2.34.dist-info/WHEEL
iris_pgwire-1.2.34.dist-info/entry_points.txt
iris_pgwire-1.2.34.dist-info/licenses/LICENSE
iris_pgwire-1.2.34.dist-info/RECORD
