Metadata-Version: 2.4
Name: iris-pgwire
Version: 1.2.34
Summary: PostgreSQL Wire Protocol Server for InterSystems IRIS - Connect BI tools, Python frameworks, and PostgreSQL clients to IRIS databases
Project-URL: Homepage, https://github.com/intersystems-community/iris-pgwire
Project-URL: Documentation, https://github.com/intersystems-community/iris-pgwire#readme
Project-URL: Repository, https://github.com/intersystems-community/iris-pgwire
Project-URL: Issues, https://github.com/intersystems-community/iris-pgwire/issues
Project-URL: Changelog, https://github.com/intersystems-community/iris-pgwire/releases
Author-email: Thomas Dyar <thomas.dyar@intersystems.com>
Maintainer-email: Thomas Dyar <thomas.dyar@intersystems.com>
License: MIT License
License-File: LICENSE
Keywords: async,bi-tools,database,fastapi,intersystems,iris,llm,pgvector,postgres,postgresql,rag,sql,sqlalchemy,vector-database,wire-protocol
Classifier: Development Status :: 5 - Production/Stable
Classifier: Framework :: AsyncIO
Classifier: Framework :: FastAPI
Classifier: Intended Audience :: Developers
Classifier: Intended Audience :: System Administrators
Classifier: License :: OSI Approved :: MIT License
Classifier: Operating System :: OS Independent
Classifier: Programming Language :: Python :: 3
Classifier: Programming Language :: Python :: 3 :: Only
Classifier: Programming Language :: Python :: 3.11
Classifier: Programming Language :: Python :: 3.12
Classifier: Topic :: Database
Classifier: Topic :: Database :: Database Engines/Servers
Classifier: Topic :: Software Development :: Libraries :: Python Modules
Classifier: Topic :: System :: Networking
Classifier: Typing :: Typed
Requires-Python: >=3.11
Requires-Dist: cryptography>=41.0.0
Requires-Dist: intersystems-irispython>=5.1.2
Requires-Dist: opentelemetry-api>=1.20.0
Requires-Dist: opentelemetry-exporter-otlp>=1.20.0
Requires-Dist: opentelemetry-instrumentation-asyncio>=0.41b0
Requires-Dist: opentelemetry-sdk>=1.20.0
Requires-Dist: prometheus-client>=0.17.0
Requires-Dist: psycopg2-binary>=2.9.10
Requires-Dist: pydantic>=2.0.0
Requires-Dist: pyyaml>=6.0.0
Requires-Dist: sqlparse>=0.4.0
Requires-Dist: structlog>=23.0.0
Provides-Extra: dev
Requires-Dist: black>=23.0.0; extra == 'dev'
Requires-Dist: mypy>=1.5.0; extra == 'dev'
Requires-Dist: ruff>=0.1.0; extra == 'dev'
Provides-Extra: iris
Provides-Extra: kerberos
Requires-Dist: gssapi>=1.8.0; extra == 'kerberos'
Provides-Extra: test
Requires-Dist: docker>=6.0.0; extra == 'test'
Requires-Dist: iris-devtester>=0.1.0; extra == 'test'
Requires-Dist: k5test>=0.10.3; extra == 'test'
Requires-Dist: psycopg[binary]>=3.1.0; extra == 'test'
Requires-Dist: pytest-asyncio>=0.21.0; extra == 'test'
Requires-Dist: pytest-benchmark>=4.0.0; extra == 'test'
Requires-Dist: pytest-cov>=4.1.0; extra == 'test'
Requires-Dist: pytest-timeout>=2.2.0; extra == 'test'
Requires-Dist: pytest>=7.0.0; extra == 'test'
Requires-Dist: sqlparse>=0.4.0; extra == 'test'
